{
  "$schema": "https://ui.shadcn.com/schema/registry-item.json",
  "name": "theme-retro-arcade",
  "title": "Retro Arcade",
  "description": "Retro arcade gaming aesthetic",
  "files": [
    {
      "path": "registry/themes/retro-arcade.css",
      "content": "/* Retro Arcade Theme - Auto-generated from tweakcn */\n\n/* Light mode */\n[data-theme=\"retro-arcade-light\"] {\n  --background: oklch(0.97 0.03 90.1);\n  --foreground: oklch(0.31 0.05 219.65);\n  --card: oklch(0.93 0.03 92.4);\n  --card-foreground: oklch(0.31 0.05 219.65);\n  --popover: oklch(0.93 0.03 92.4);\n  --popover-foreground: oklch(0.31 0.05 219.65);\n  --primary: oklch(0.59 0.2 355.89);\n  --primary-foreground: oklch(1 0 0);\n  --secondary: oklch(0.64 0.1 187.38);\n  --secondary-foreground: oklch(1 0 0);\n  --muted: oklch(0.7 0.02 196.79);\n  --muted-foreground: oklch(0.31 0.05 219.65);\n  --accent: oklch(0.58 0.17 39.5);\n  --accent-foreground: oklch(1 0 0);\n  --destructive: oklch(0.59 0.21 27.12);\n  --destructive-foreground: oklch(1 0 0);\n  --border: oklch(0.65 0.02 205.26);\n  --input: oklch(0.65 0.02 205.26);\n  --ring: oklch(0.59 0.2 355.89);\n  --chart-1: oklch(0.61 0.14 244.93);\n  --chart-2: oklch(0.64 0.1 187.38);\n  --chart-3: oklch(0.59 0.2 355.89);\n  --chart-4: oklch(0.58 0.17 39.5);\n  --chart-5: oklch(0.59 0.21 27.12);\n  --radius: 0.25rem;\n  --sidebar: oklch(0.97 0.03 90.1);\n  --sidebar-foreground: oklch(0.31 0.05 219.65);\n  --sidebar-primary: oklch(0.59 0.2 355.89);\n  --sidebar-primary-foreground: oklch(1 0 0);\n  --sidebar-accent: oklch(0.64 0.1 187.38);\n  --sidebar-accent-foreground: oklch(1 0 0);\n  --sidebar-border: oklch(0.65 0.02 205.26);\n  --sidebar-ring: oklch(0.59 0.2 355.89);\n  --font-sans: Outfit, sans-serif;\n  --font-serif: ui-serif, Georgia, Cambria, \"Times New Roman\", Times, serif;\n  --font-mono: Space Mono, monospace;\n  --shadow-color: hsl(196 83% 10%);\n  --shadow-opacity: 0.15;\n  --shadow-blur: 4px;\n  --shadow-spread: 0px;\n  --shadow-offset-x: 2px;\n  --shadow-offset-y: 2px;\n  --letter-spacing: 0em;\n  --spacing: 0.25rem;\n  --shadow-2xs: 2px 2px 4px 0px hsl(196 83% 10% / 0.07);\n  --shadow-xs: 2px 2px 4px 0px hsl(196 83% 10% / 0.07);\n  --shadow-sm:\n    2px 2px 4px 0px hsl(196 83% 10% / 0.15),\n    2px 1px 2px -1px hsl(196 83% 10% / 0.15);\n  --shadow:\n    2px 2px 4px 0px hsl(196 83% 10% / 0.15),\n    2px 1px 2px -1px hsl(196 83% 10% / 0.15);\n  --shadow-md:\n    2px 2px 4px 0px hsl(196 83% 10% / 0.15),\n    2px 2px 4px -1px hsl(196 83% 10% / 0.15);\n  --shadow-lg:\n    2px 2px 4px 0px hsl(196 83% 10% / 0.15),\n    2px 4px 6px -1px hsl(196 83% 10% / 0.15);\n  --shadow-xl:\n    2px 2px 4px 0px hsl(196 83% 10% / 0.15),\n    2px 8px 10px -1px hsl(196 83% 10% / 0.15);\n  --shadow-2xl: 2px 2px 4px 0px hsl(196 83% 10% / 0.38);\n  --tracking-normal: 0em;\n}\n\n/* Dark mode */\n[data-theme=\"retro-arcade-dark\"] {\n  --background: oklch(0.27 0.05 219.82);\n  --foreground: oklch(0.7 0.02 196.79);\n  --card: oklch(0.31 0.05 219.65);\n  --card-foreground: oklch(0.7 0.02 196.79);\n  --popover: oklch(0.31 0.05 219.65);\n  --popover-foreground: oklch(0.7 0.02 196.79);\n  --primary: oklch(0.59 0.2 355.89);\n  --primary-foreground: oklch(1 0 0);\n  --secondary: oklch(0.64 0.1 187.38);\n  --secondary-foreground: oklch(1 0 0);\n  --muted: oklch(0.52 0.03 219.14);\n  --muted-foreground: oklch(0.7 0.02 196.79);\n  --accent: oklch(0.58 0.17 39.5);\n  --accent-foreground: oklch(1 0 0);\n  --destructive: oklch(0.59 0.21 27.12);\n  --destructive-foreground: oklch(1 0 0);\n  --border: oklch(0.52 0.03 219.14);\n  --input: oklch(0.52 0.03 219.14);\n  --ring: oklch(0.59 0.2 355.89);\n  --chart-1: oklch(0.61 0.14 244.93);\n  --chart-2: oklch(0.64 0.1 187.38);\n  --chart-3: oklch(0.59 0.2 355.89);\n  --chart-4: oklch(0.58 0.17 39.5);\n  --chart-5: oklch(0.59 0.21 27.12);\n  --radius: 0.25rem;\n  --sidebar: oklch(0.27 0.05 219.82);\n  --sidebar-foreground: oklch(0.7 0.02 196.79);\n  --sidebar-primary: oklch(0.59 0.2 355.89);\n  --sidebar-primary-foreground: oklch(1 0 0);\n  --sidebar-accent: oklch(0.64 0.1 187.38);\n  --sidebar-accent-foreground: oklch(1 0 0);\n  --sidebar-border: oklch(0.52 0.03 219.14);\n  --sidebar-ring: oklch(0.59 0.2 355.89);\n  --font-sans: Outfit, sans-serif;\n  --font-serif: ui-serif, Georgia, Cambria, \"Times New Roman\", Times, serif;\n  --font-mono: Space Mono, monospace;\n  --shadow-color: hsl(196 83% 10%);\n  --shadow-opacity: 0.15;\n  --shadow-blur: 4px;\n  --shadow-spread: 0px;\n  --shadow-offset-x: 2px;\n  --shadow-offset-y: 2px;\n  --letter-spacing: 0em;\n  --spacing: 0.25rem;\n  --shadow-2xs: 2px 2px 4px 0px hsl(196 83% 10% / 0.07);\n  --shadow-xs: 2px 2px 4px 0px hsl(196 83% 10% / 0.07);\n  --shadow-sm:\n    2px 2px 4px 0px hsl(196 83% 10% / 0.15),\n    2px 1px 2px -1px hsl(196 83% 10% / 0.15);\n  --shadow:\n    2px 2px 4px 0px hsl(196 83% 10% / 0.15),\n    2px 1px 2px -1px hsl(196 83% 10% / 0.15);\n  --shadow-md:\n    2px 2px 4px 0px hsl(196 83% 10% / 0.15),\n    2px 2px 4px -1px hsl(196 83% 10% / 0.15);\n  --shadow-lg:\n    2px 2px 4px 0px hsl(196 83% 10% / 0.15),\n    2px 4px 6px -1px hsl(196 83% 10% / 0.15);\n  --shadow-xl:\n    2px 2px 4px 0px hsl(196 83% 10% / 0.15),\n    2px 8px 10px -1px hsl(196 83% 10% / 0.15);\n  --shadow-2xl: 2px 2px 4px 0px hsl(196 83% 10% / 0.38);\n}\n",
      "type": "registry:file",
      "target": "styles/themes/retro-arcade.css"
    }
  ],
  "type": "registry:theme"
}